pybeamline_real_sources/__init__.py
pybeamline_real_sources/ais.py
pybeamline_real_sources/rejseplanen.py
pybeamline_real_sources/wikimedia.py
pybeamline_real_sources-0.1.0.dist-info/METADATA
pybeamline_real_sources-0.1.0.dist-info/WHEEL
pybeamline_real_sources-0.1.0.dist-info/top_level.txt
pybeamline_real_sources-0.1.0.dist-info/RECORD
