Metadata-Version: 2.4
Name: pybeamline-real-sources
Version: 0.1.0
Summary: Real stream sources for pyBeamline
Author: Andrea Burattin
Project-URL: Homepage, https://beamline.cloud/
Project-URL: Issues, https://github.com/beamline/pybeamline-real-sources/issues
Requires-Python: >=3.9
Requires-Dist: pybeamline>=2.0.0
Provides-Extra: dev
Requires-Dist: build; extra == "dev"
Requires-Dist: pip-tools; extra == "dev"
